pysarcat-1.0.6.data/data/scita_classification/data/cats.json
pysarcat-1.0.6.data/data/scita_classification/data/mcat_dict.json
sarcat/__init__.py
sarcat/inference.py
sarcat/losses.py
sarcat/options.py
sarcat/train.py
sarcat/train_bert.py
sarcat/api/api_sarcat.py
sarcat/api/classification.py
sarcat/models/__init__.py
sarcat/models/bert2.py
sarcat/models/bert_models.py
sarcat/models/modules.py
sarcat/models/rnn_models.py
sarcat/models/legacy/cats.json
sarcat/models/legacy/db.py
sarcat/models/legacy/inference.py
sarcat/models/legacy/mcat_dict.json
sarcat/models/legacy/modules.py
sarcat/models/legacy/utils.py
sarcat/models/s2fos/__init__.py
sarcat/models/s2fos/model.py
sarcat/models/s2fos/utils.py
sarcat/predictions/__init__.py
sarcat/predictions/classification.py
sarcat/predictions/utils.py
pysarcat-1.0.6.dist-info/LICENSE
pysarcat-1.0.6.dist-info/METADATA
pysarcat-1.0.6.dist-info/WHEEL
pysarcat-1.0.6.dist-info/top_level.txt
pysarcat-1.0.6.dist-info/RECORD
