Metadata-Version: 2.1
Name: pysarcat
Version: 1.0.6
Summary: Sientific papers  categorization.
Home-page: https://github.com/opscidia/scita-classification.git
Maintainer: Opscidia
Maintainer-email: frejus.laleye@opscidia.com
License: UNKNOWN
Project-URL: Bug Tracker, https://github.com/opscidia/scita-classification/issues
Project-URL: Source Code, https://github.com/opscidia/scita-classification/
Keywords: Opscidia NLP deep learning scientific paper categorization field topic study
Platform: UNKNOWN
Classifier: Intended Audience :: Science/Research
Classifier: Development Status :: 3 - Alpha
Classifier: License :: OSI Approved :: Apache Software License
Classifier: Programming Language :: Python :: 3.7
Classifier: Topic :: Scientific/Engineering :: Artificial Intelligence
Requires-Python: >=3.7
License-File: LICENSE
Requires-Dist: torch (==1.12.0)
Requires-Dist: torchtext (==0.13.0)
Requires-Dist: spacy (==3.0.9)
Requires-Dist: scikit-learn (==1.0.2)
Requires-Dist: flask-restful
Requires-Dist: numpy (==1.21.6)
Requires-Dist: sklearn-contrib-lightning (==0.6.2.post0)
Requires-Dist: text-unidecode
Requires-Dist: pandas (==1.3.5)
Requires-Dist: fasttext (==0.9.2)
Requires-Dist: pycld2 (==0.41)
Requires-Dist: pydantic (==1.8.2)
